{
  "collapse-filter": true,
  "search": "tag:#tags ",
  "showTags": false,
  "showAttachments": false,
  "hideUnresolved": true,
  "showOrphans": true,
  "collapse-color-groups": true,
  "colorGroups": [
    {
      "query": "tag:#book  ",
      "color": {
        "a": 1,
        "rgb": 14048348
      }
    },
    {
      "query": "path:\"computer science\"  ",
      "color": {
        "a": 1,
        "rgb": 14069084
      }
    },
    {
      "query": "path:physics  ",
      "color": {
        "a": 1,
        "rgb": 11392604
      }
    },
    {
      "query": "path:chemistry  ",
      "color": {
        "a": 1,
        "rgb": 6084188
      }
    },
    {
      "query": "path:biology  ",
      "color": {
        "a": 1,
        "rgb": 6084269
      }
    },
    {
      "query": "path:medicine  ",
      "color": {
        "a": 1,
        "rgb": 6073814
      }
    },
    {
      "query": "path:economics  ",
      "color": {
        "a": 1,
        "rgb": 6053078
      }
    },
    {
      "query": "path:linguistics  ",
      "color": {
        "a": 1,
        "rgb": 11361494
      }
    },
    {
      "query": "path:engineering/genetic path:",
      "color": {
        "a": 1,
        "rgb": 14048429
      }
    },
    {
      "query": "path:engineering/computer  ",
      "color": {
        "a": 1,
        "rgb": 15142234
      }
    },
    {
      "query": "path:engineering/software  ",
      "color": {
        "a": 1,
        "rgb": 16731392
      }
    },
    {
      "query": "path:engineering/electrical  ",
      "color": {
        "a": 1,
        "rgb": 16774912
      }
    },
    {
      "query": "path:engineering/industrial  ",
      "color": {
        "a": 1,
        "rgb": 8453888
      }
    },
    {
      "query": "path:law  ",
      "color": {
        "a": 1,
        "rgb": 65356
      }
    },
    {
      "query": "path:history  ",
      "color": {
        "a": 1,
        "rgb": 64511
      }
    },
    {
      "query": "path:philosophy  ",
      "color": {
        "a": 1,
        "rgb": 28415
      }
    },
    {
      "query": "path:math  ",
      "color": {
        "a": 1,
        "rgb": 16711927
      }
    }
  ],
  "collapse-display": true,
  "showArrow": true,
  "textFadeMultiplier": -3,
  "nodeSizeMultiplier": 1.33762886597938,
  "lineSizeMultiplier": 3.51979166666667,
  "collapse-forces": true,
  "centerStrength": 0.505208333333333,
  "repelStrength": 17.9166666666667,
  "linkStrength": 1,
  "linkDistance": 265,
  "scale": 0.4060727265206227,
  "close": false
}